{
  "textures": {
    "levelsBackground": "images/LevelSelectBackground.png",
    "levelsTray": "images/LevelSelectTray.png",
    "coin": {
      "file": "images/coin.png",
      "sprites": {
        "animation": {
          "rows": 1,
          "cols": 22,
          "size": 22
        }
      }
    },
    "plusOne": {
      "file": "images/+1.png",
      "sprites": {
        "animation": {
          "rows": 1,
          "cols": 6,
          "size": 6
        }
      }
    },
    "idleMouse": {
      "file": "images/Boss_Rat_IdleStatic.png",
      "sprites": {
        "animation": {
          "rows": 1,
          "cols": 1,
          "size": 1
        }
      }
    },
    "dashMouseVertical": {
      "file": "images/Boss_Rat_RunDown.png",
      "sprites": {
        "animation": {
          "rows": 1,
          "cols": 5,
          "size": 5
        }
      }
    },
    "dashMouseHorizontal": {
      "file": "images/Boss_Rat_RunHorizontal.png",
      "sprites": {
        "animation": {
          "rows": 1,
          "cols": 5,
          "size": 5
        }
      }
    },
    "spinMouse": {
      "file": "images/MouseSpin.png",
      "sprites": {
        "animation": {
          "rows": 1,
          "cols": 4,
          "size": 4
        }
      }
    },
    "deathMouse": {
      "file": "images/MouseDeath.png",
      "sprites": {
        "animation": {
          "rows": 1,
          "cols": 6,
          "size": 6
        }
      }
    },
    "idleChopsticks": {
      "file": "images/Boss_Chopsticks_Static.png",
      "sprites": {
        "animation": {
          "rows": 1,
          "cols": 1,
          "size": 1
        }
      }
    },
    "dashChopsticks": {
      "file": "images/Boss_Chopstick_Dash.png",
      "sprites": {
        "animation": {
          "rows": 1,
          "cols": 4,
          "size": 4
        }
      }
    },
    "dashWarnVertical": {
      "file": "images/DashWarnVertical.png",
      "sprites": {
        "animation": {
          "rows": 1,
          "cols": 2,
          "size": 2
        }
      }
    },
    "dashWarnHorizontal": {
      "file": "images/DashWarnHorizontal.png",
      "sprites": {
        "animation": {
          "rows": 2,
          "cols": 1,
          "size": 2
        }
      }
    },
    "spinWarn": {
      "file": "images/SpinWarn.png",
      "sprites": {
        "animation": {
          "rows": 1,
          "cols": 2,
          "size": 2
        }
      }
    },
    "idleWarn": {
      "file": "images/idleWarn.png",
      "sprites": {
        "animation": {
          "rows": 1,
          "cols": 2,
          "size": 2
        }
      }
    },
    "headDirStill": "images/UI_HeadIndicator_Still.PNG",
    "headDirUp": "images/UI_HeadIndicator_Up.PNG",
    "headDirDown": "images/UI_HeadIndicator_Down.PNG",
    "headDirLeft": "images/UI_HeadIndicator_Left.PNG",
    "headDirRight": "images/UI_HeadIndicator_Right.PNG",
    "AVOCADO": {
      "file": "images/Avocado.png",
      "sprites": {
        "animation": {
          "rows": 1,
          "cols": 8,
          "size": 8
        }
      }
    },
    "BLUE_RASPBERRY": {
      "file": "images/BlueRaspberry.png",
      "sprites": {
        "animation": {
          "rows": 1,
          "cols": 8,
          "size": 8
        }
      }
    },
    "DURIAN": {
      "file": "images/Durian.png",
      "sprites": {
        "animation": {
          "rows": 1,
          "cols": 8,
          "size": 8
        }
      }
    },
    "GARLIC": {
      "file": "images/Garlic.png",
      "sprites": {
        "animation": {
          "rows": 1,
          "cols": 7,
          "size": 7
        }
      }
    },
    "PINEAPPLE": {
      "file": "images/Pineapple.png",
      "sprites": {
        "animation": {
          "rows": 1,
          "cols": 8,
          "size": 8
        }
      }
    },
    "STRAWBERRY": {
      "file": "images/Strawberry.png",
      "sprites": {
        "animation": {
          "rows": 1,
          "cols": 8,
          "size": 8
        }
      }
    },
    "companionDeath": {
      "file": "images/Companion_Death_Universal.png",
      "sprites": {
        "animation": {
          "rows": 1,
          "cols": 6,
          "size": 6
        }
      }
    },
    "progress": {
      "file": "images/hpBar.png",
      "atlas": {
        "back": [
          0,
          0,
          523,
          33
        ],
        "foreground": [
          27,
          34,
          496,
          68
        ],
        "foreleft": [
          0,
          34,
          27,
          68
        ],
        "foreright": [
          496,
          34,
          523,
          68
        ]
      }
    },
    "plate": "images/LevelSelectPlate.png",
    "plateHover": "images/LevelSelectPlate.png",
    "lock": "images/Lock.png",
    "arrow": "images/NextButton.png",
    "arrowHover": "images/NextButtonHover.png",
    "settings": "images/HandbookButton.png",
    "settingsHover": "images/HandbookButtonHover.png",
    "home": "images/HomeButton.png",
    "homeHover": "images/HomeButtonHover.png",
    "handbook": "images/HandbookButton.png",
    "handbookHover": "images/HandbookButtonHover.png",
    "Handbook0": {
      "file": "images/HandbookAvocado.png",
      "sprites": {
        "animation": {
          "rows": 1,
          "cols": 2,
          "size": 2
        }
      }
    },
    "Handbook1": {
      "file": "images/HandbookAvocado.png",
      "sprites": {
        "animation": {
          "rows": 1,
          "cols": 2,
          "size": 2
        }
      }
    },
    "Handbook2": {
      "file": "images/HandbookAvocado.png",
      "sprites": {
        "animation": {
          "rows": 1,
          "cols": 2,
          "size": 2
        }
      }
    },
    "Handbook3": {
      "file": "images/HandbookAvocado.png",
      "sprites": {
        "animation": {
          "rows": 1,
          "cols": 2,
          "size": 2
        }
      }
    },
    "Handbook4": {
      "file": "images/HandbookAvocado.png",
      "sprites": {
        "animation": {
          "rows": 1,
          "cols": 2,
          "size": 2
        }
      }
    }
  },
  "fonts": {
    "lpc": {
      "file": "fonts/LPC.ttf",
      "size": 25
    },
    "lpcBig": {
      "file": "fonts/LPC.ttf",
      "size": 40
    }
  },
  "jsons": {
    "constants": "jsons/constants.json",
    "save": "jsons/savedGame.json"
  },
  "soundfx": {
    "click": "sounds/click.wav",
    "clickLevel": "sounds/clickLevel.wav",
    "coin": "sounds/collectCoin.wav",
    "durian": "sounds/durianAttack.wav",
    "strawberry": "sounds/strawberryAttack.wav",
    "mouseAttack": "sounds/ratAttack.wav",
    "chefAttack": "sounds/chefAttack.wav",
    "chopsticksAttack": "sounds/chopsticksAttack.wav",
    "mouseDeath": "sounds/ratDeath.wav",
    "chefDeath": "sounds/chefDeath.wav",
    "chopsticksDeath": "sounds/chopsticksDeath.wav",
    "minionDeath": "sounds/minionDeath.wav",
    "companionDeath": "sounds/companionDeath.wav",
    "companionRecruitment": "sounds/collectCompanion.wav"
  },
  "samples": {
    "menu": "sounds/menu.ogg",
    "levels": "sounds/levels.ogg",
    "handbook": "sounds/handbook.ogg",
    "preLevel": "sounds/preLevel.ogg",
    "mouseLevel": "sounds/mouseLevel.ogg",
    "chefLevel": "sounds/chefLevel.ogg",
    "chopsticksLevel": "sounds/chopsticksLevel.ogg",
    "win": "sounds/win.ogg",
    "lose": "sounds/lose.ogg"
  }
}
